{
    "bean": {
        "_v": 0,
        "addr": "n1747969945.xlxzzx.com",
        "aid": 0,
        "brutal_speed": 0,
        "c_cfg": "",
        "c_out": "",
        "enable_brutal": false,
        "id": "192217b5-fd9f-4e08-9c74-1726f83af848",
        "mux": 0,
        "name": "🇭🇰HK-47.76.170.153-0284",
        "port": 443,
        "sec": "auto",
        "stream": {
            "alpn": "",
            "cert": "",
            "ed_len": 0,
            "ed_name": "",
            "h_type": "auto",
            "headers": "",
            "host": "n1747969945.xlxzzx.com",
            "insecure": false,
            "method": "",
            "net": "ws",
            "pac_enc": "",
            "path": "/",
            "pbk": "",
            "sec": "tls",
            "sid": "",
            "sni": "n1747969945.xlxzzx.com",
            "tls_frag": false,
            "tls_frag_fall_delay": "",
            "tls_record_frag": false,
            "utls": ""
        }
    },
    "country": "",
    "dl": "",
    "gid": 9,
    "id": 11337,
    "report": "",
    "traffic": {
        "dl": 0,
        "ul": 0
    },
    "type": "vmess",
    "ul": "",
    "yc": -1
}
