{
    "bean": {
        "_v": 0,
        "addr": "n1744453319.lie5d.cyou",
        "aid": 0,
        "brutal_speed": 0,
        "c_cfg": "",
        "c_out": "",
        "enable_brutal": false,
        "id": "6928af97-a23e-408c-956e-5cd2207f3557",
        "mux": 0,
        "name": "🇭🇰HK-47.242.26.144-0304",
        "port": 443,
        "sec": "auto",
        "stream": {
            "alpn": "",
            "cert": "",
            "ed_len": 0,
            "ed_name": "",
            "h_type": "auto",
            "headers": "",
            "host": "n1744453319.lie5d.cyou",
            "insecure": false,
            "method": "",
            "net": "ws",
            "pac_enc": "",
            "path": "/",
            "pbk": "",
            "sec": "tls",
            "sid": "",
            "sni": "n1744453319.lie5d.cyou",
            "tls_frag": false,
            "tls_frag_fall_delay": "",
            "tls_record_frag": false,
            "utls": ""
        }
    },
    "country": "",
    "dl": "",
    "gid": 9,
    "id": 11985,
    "report": "",
    "traffic": {
        "dl": 0,
        "ul": 0
    },
    "type": "vmess",
    "ul": "",
    "yc": -1
}
