{
    "bean": {
        "_v": 0,
        "addr": "47.250.45.234",
        "aid": 0,
        "brutal_speed": 0,
        "c_cfg": "",
        "c_out": "",
        "enable_brutal": false,
        "id": "80039b4d-bac0-4f89-82c7-54fad3b0a1ea",
        "mux": 0,
        "name": "🇲🇾MY-47.250.45.234-5027",
        "port": 8613,
        "sec": "auto",
        "stream": {
            "alpn": "",
            "cert": "",
            "ed_len": 0,
            "ed_name": "",
            "h_type": "auto",
            "headers": "",
            "host": "",
            "insecure": false,
            "method": "",
            "net": "ws",
            "pac_enc": "",
            "path": "/arki?ed=2048",
            "pbk": "",
            "sec": "",
            "sid": "",
            "sni": "",
            "tls_frag": false,
            "tls_frag_fall_delay": "",
            "tls_record_frag": false,
            "utls": ""
        }
    },
    "country": "",
    "dl": "",
    "gid": 9,
    "id": 13214,
    "report": "",
    "traffic": {
        "dl": 0,
        "ul": 0
    },
    "type": "vmess",
    "ul": "",
    "yc": -1
}
