{
    "bean": {
        "_v": 0,
        "addr": "37.27.24.154.213.254.1ta8.online",
        "brutal_speed": 0,
        "c_cfg": "",
        "c_out": "",
        "enable_brutal": false,
        "flow": "xtls-rprx-vision",
        "mux": 0,
        "name": "🇫🇮[Telegram:@tik7net_vpn]",
        "pass": "015c9cef-5936-4445-aca7-e846479992aa",
        "port": 8080,
        "stream": {
            "alpn": "",
            "cert": "",
            "ed_len": 0,
            "ed_name": "",
            "h_type": "",
            "headers": "",
            "host": "",
            "insecure": false,
            "method": "",
            "net": "tcp",
            "pac_enc": "xudp",
            "path": "",
            "pbk": "rEHTPGOMI9UKT-W__dvCkITykQFNAh0SY2za-pa241Q",
            "sec": "tls",
            "sid": "cf38b7bf1ab08fa4",
            "sni": "tgju.org",
            "tls_frag": false,
            "tls_frag_fall_delay": "",
            "tls_record_frag": false,
            "utls": "firefox"
        }
    },
    "country": "",
    "dl": "",
    "gid": 1,
    "id": 154,
    "report": "",
    "traffic": {
        "dl": 0,
        "ul": 0
    },
    "type": "vless",
    "ul": "",
    "yc": 84
}
