{
    "bean": {
        "_v": 0,
        "addr": "medium.com",
        "brutal_speed": 0,
        "c_cfg": "",
        "c_out": "",
        "enable_brutal": false,
        "flow": "",
        "mux": 0,
        "name": "[🇭🇰] [vl-tl-ws] [251026-102240.633]",
        "pass": "17108cd5-ddcf-4b6e-bb43-36a711a01366",
        "port": 443,
        "stream": {
            "alpn": "",
            "cert": "",
            "ed_len": 0,
            "ed_name": "",
            "h_type": "",
            "headers": "",
            "host": "rAyAn-cOnFiG-HK-1.pArSa.dPdNs.oRg",
            "insecure": false,
            "method": "",
            "net": "ws",
            "pac_enc": "xudp",
            "path": "/ws",
            "pbk": "",
            "sec": "tls",
            "sid": "",
            "sni": "rAyAn-cOnFiG-HK-1.pArSa.dPdNs.oRg",
            "tls_frag": false,
            "tls_frag_fall_delay": "",
            "tls_record_frag": false,
            "utls": "chrome"
        }
    },
    "country": "",
    "dl": "",
    "gid": 6,
    "id": 4040,
    "report": "",
    "traffic": {
        "dl": 0,
        "ul": 0
    },
    "type": "vless",
    "ul": "",
    "yc": 0
}
