{
    "bean": {
        "_v": 0,
        "addr": "104.20.5.134",
        "brutal_speed": 0,
        "c_cfg": "",
        "c_out": "",
        "enable_brutal": false,
        "flow": "",
        "mux": 0,
        "name": "🇽🇽XX(AzadNet.t.me)",
        "pass": "6c0ed3fb-f0b0-5b53-a762-f8f8d832bdba",
        "port": 2083,
        "stream": {
            "alpn": "",
            "cert": "",
            "ed_len": 0,
            "ed_name": "",
            "h_type": "",
            "headers": "",
            "host": "",
            "insecure": false,
            "method": "",
            "net": "tcp",
            "pac_enc": "",
            "path": "",
            "pbk": "",
            "sec": "tls",
            "sid": "",
            "sni": "vfarid.xcdi.wOrKERS.DEV",
            "tls_frag": false,
            "tls_frag_fall_delay": "",
            "tls_record_frag": false,
            "utls": ""
        }
    },
    "country": "",
    "dl": "",
    "gid": 3,
    "id": 6459,
    "report": "",
    "traffic": {
        "dl": 0,
        "ul": 0
    },
    "type": "trojan",
    "ul": "",
    "yc": 0
}
