{"version":1,"resource":"file:///home/mrboomdev/VSCodeProjects/Website/Website/src/assets/android.svg","entries":[{"id":"rrEE.svg","timestamp":1765929385541},{"id":"arVU.svg","timestamp":1765929476983},{"id":"AjyT.svg","timestamp":1765929551280},{"id":"75Ny.svg","timestamp":1765929610212},{"id":"AVPW.svg","timestamp":1765930985594},{"id":"xJoV.svg","timestamp":1765931038767},{"id":"lqz5.svg","timestamp":1765932448572},{"id":"ufPI.svg","source":"undoRedo.source","timestamp":1765932453899},{"id":"29B9.svg","timestamp":1765932461934},{"id":"yhas.svg","source":"undoRedo.source","timestamp":1765932465551}]}